{"cpu_time": -1, "total_cpu_time": null, "wallclock_time": 67.35216093063354, "evaluations": 0, "cost": 1.0585122108459473, "incumbent": ["batch_size='231'", "channel_1='15'", "channel_2='3'", "n_fc_layer='3'", "fc_nodes='53'"], "origin": "Random"}
{"cpu_time": -1, "total_cpu_time": null, "wallclock_time": 119.51013135910034, "evaluations": 0, "cost": 0.8496960997581482, "incumbent": ["batch_size='257'", "channel_1='9'", "channel_2='3'", "n_fc_layer='2'", "fc_nodes='51'"], "origin": "Random"}
{"cpu_time": -1, "total_cpu_time": null, "wallclock_time": 181.19021439552307, "evaluations": 0, "cost": 0.5956897735595703, "incumbent": ["batch_size='225'", "channel_1='17'", "channel_2='1'", "n_fc_layer='1'"], "origin": "Random"}
{"cpu_time": -1, "total_cpu_time": null, "wallclock_time": 250.8968629837036, "evaluations": 0, "cost": 0.5265423655509949, "incumbent": ["batch_size='815'", "channel_1='18'", "channel_2='4'", "n_fc_layer='3'", "fc_nodes='201'"], "origin": "Random"}
{"cpu_time": -1, "total_cpu_time": null, "wallclock_time": 312.72858715057373, "evaluations": 0, "cost": 0.4411420226097107, "incumbent": ["batch_size='265'", "channel_1='15'", "channel_2='3'", "n_fc_layer='1'"], "origin": "Random"}
{"cpu_time": -1, "total_cpu_time": null, "wallclock_time": 657.4360587596893, "evaluations": 0, "cost": 0.3334220051765442, "incumbent": ["batch_size='262'", "channel_1='12'", "channel_2='4'", "n_fc_layer='3'", "fc_nodes='739'"], "origin": "Random"}
{"cpu_time": -1, "total_cpu_time": null, "wallclock_time": 968.1510376930237, "evaluations": 0, "cost": 0.3059351146221161, "incumbent": ["batch_size='448'", "channel_1='18'", "channel_2='4'", "n_fc_layer='2'", "fc_nodes='574'"], "origin": "Model based pick"}
{"cpu_time": -1, "total_cpu_time": null, "wallclock_time": 7348.4082753658295, "evaluations": 0, "cost": 0.29196467995643616, "incumbent": ["batch_size='144'", "channel_1='13'", "channel_2='4'", "n_fc_layer='2'", "fc_nodes='620'"], "origin": "Model based pick"}
{"cpu_time": -1, "total_cpu_time": null, "wallclock_time": 15396.832485198975, "evaluations": 0, "cost": 0.27532684803009033, "incumbent": ["batch_size='136'", "channel_1='17'", "channel_2='4'", "n_fc_layer='2'", "fc_nodes='550'"], "origin": "Model based pick"}
{"cpu_time": -1, "total_cpu_time": null, "wallclock_time": 16398.294372320175, "evaluations": 0, "cost": 0.2705405056476593, "incumbent": ["batch_size='184'", "channel_1='19'", "channel_2='4'", "n_fc_layer='2'", "fc_nodes='586'"], "origin": "Model based pick"}
{"cpu_time": -1, "total_cpu_time": null, "wallclock_time": 18743.41960310936, "evaluations": 0, "cost": 0.2705405056476593, "incumbent": ["batch_size='184'", "channel_1='19'", "channel_2='4'", "n_fc_layer='2'", "fc_nodes='586'"], "origin": "Model based pick"}
